mgimo/__init__.py
mgimo/cli.py
mgimo/dataset/__init__.py
mgimo/dataset/make.py
mgimo/dataset/data/__init__.py
mgimo/dataset/data/capital_cities_en.csv
mgimo/dataset/data/countries_en.csv
mgimo/dataset/data/countries_ru.csv
mgimo/dataset/data/countries_ru.py
mgimo/quiz/__init__.py
mgimo/quiz/capitals.py
mgimo/translate/__init__.py
mgimo/translate/app.py
mgimo/translate/constants.py
mgimo/translate/engine.py
mgimo/utils/__init__.py
mgimo/utils/grading.py
mgimo/utils/logging.py
mgimo/utils/main.py
mgimo-0.6.0.dist-info/METADATA
mgimo-0.6.0.dist-info/WHEEL
mgimo-0.6.0.dist-info/entry_points.txt
mgimo-0.6.0.dist-info/RECORD
