Metadata-Version: 2.4
Name: mgimo
Version: 0.6.0
Summary: MGIMO datasets and Python utilities.
Requires-Python: >=3.10
Requires-Dist: deep-translator>=1.11.4
Requires-Dist: docopt>=0.6.2
Requires-Dist: langdetect>=1.0.9
Requires-Dist: pandas>=2.3.3
